{
    "contacts": "cva",
    "labels": "g4",
    "add_label": "d6c",
    "label": "d69",
    "contacts_count_by_label": "d68",
    "friend_remark_by_label": "foi",
    "friend_list_by_label": "android:id/list",
    "delete_label": "android:id/title",
    "back_to_label_list": "du",
    "label_list": "d6a",
    "friend_list": "fa",
    "friend_remark": "eg3",
    "contacts_count": "b1j",
    "send_message": "gtv",
    "friend_labels": "b2a",
    "friend_details_page_list": "android:id/list",
    "we_chat_id": "b4o",
    "back_to_friend_list": "du",
    "more_function_by_transfer": "amm",
    "transfer_function": "pq",
    "payee": "fiw",
    "transfer_amount": "hli",
    "confirm_transfer": "d5j",
    "close_transfer": "#",
    "abnormal_message": "e7e",
    "confirm_abnormal_message": "e7l",
    "back_to_chat": "du",
    "back_to_chats": "s8",
    "more_function_by_delete": "cq",
    "more_function_by_delete_list": "android:id/list",
    "delete": "gtv",
    "confirm_delete": "e7l"
}